mkdocs_tooltipster_links_plugin/__init__.py
mkdocs_tooltipster_links_plugin/plugin.py
mkdocs_preview_links_plugin-0.6.2.dist-info/LICENSE
mkdocs_preview_links_plugin-0.6.2.dist-info/METADATA
mkdocs_preview_links_plugin-0.6.2.dist-info/WHEEL
mkdocs_preview_links_plugin-0.6.2.dist-info/entry_points.txt
mkdocs_preview_links_plugin-0.6.2.dist-info/top_level.txt
mkdocs_preview_links_plugin-0.6.2.dist-info/RECORD
