Metadata-Version: 2.1
Name: mkdocs-preview-links-plugin
Version: 0.6.2
Summary: An MkDocs plugin that adds tooltips to preview the content of page links using tooltipster.
Home-page: https://github.com/Mara-Li/mkdocs-preview-links-plugin
Author: Mara-Li
Author-email: mara-li@outlook.fr
License: MIT
Keywords: mkdocs,preview,tooltipster,tooltipst,plugin
Classifier: Development Status :: 4 - Beta
Classifier: Intended Audience :: Developers
Classifier: Intended Audience :: Information Technology
Classifier: License :: OSI Approved :: MIT License
Classifier: Programming Language :: Python
Classifier: Programming Language :: Python :: 3 :: Only
Classifier: Programming Language :: Python :: 3.4
Classifier: Programming Language :: Python :: 3.5
Classifier: Programming Language :: Python :: 3.6
Classifier: Programming Language :: Python :: 3.7
Requires-Python: >=3.6
License-File: LICENSE
Requires-Dist: mkdocs
Requires-Dist: setuptools
Requires-Dist: Markdown
Requires-Dist: beautifulsoup4
Requires-Dist: python-frontmatter
Requires-Dist: mdx-wikilink-plus
Requires-Dist: mkdocs-callouts
Requires-Dist: mkdocs-custom-tags-attributes
